.gitignore
ChangeLog.md
LEGAL
LICENSE
LICENSE-2.0.txt
README.md
README.txt
setup.py
docs/images/IofloArchParts.png
docs/images/IofloContexts.png
docs/images/IofloReliableEnvelope.png
docs/images/IofloSysArch.png
docs/images/floscript_logo.png
docs/images/ioflo_logo.png
docs/images/ioflo_logo_black.png
docs/images/ioflo_logo_cap.png
docs/images/ioflo_o.png
docs/images/ioflo_o_recurse.png
ioflo/__init__.py
ioflo/__metadata__.py
ioflo.egg-info/dependency_links.txt
ioflo.egg-info/top_level.txt
ioflo/aid/__init__.py
ioflo/aid/aggregating.py
ioflo/aid/aiding.py
ioflo/aid/blending.py
ioflo/aid/byting.py
ioflo/aid/checking.py
ioflo/aid/classing.py
ioflo/aid/consoling.py
ioflo/aid/eventing.py
ioflo/aid/filing.py
ioflo/aid/navigating.py
ioflo/aid/odicting.py
ioflo/aid/optimizing.py
ioflo/aid/osetting.py
ioflo/aid/quaternioning.py
ioflo/aid/sixing.py
ioflo/aid/timing.py
ioflo/aid/vectoring.py
ioflo/aid/test/__init__.py
ioflo/aid/test/test_aiding.py
ioflo/aid/test/test_blending.py
ioflo/aid/test/test_byting.py
ioflo/aid/test/test_classing.py
ioflo/aid/test/test_eventing.py
ioflo/aid/test/test_odicting.py
ioflo/aid/test/test_osetting.py
ioflo/aid/test/test_quating.py
ioflo/aid/test/test_sixing.py
ioflo/aid/test/test_timing.py
ioflo/aid/test/test_vectoring.py
ioflo/aid/test/pytest/__init__.py
ioflo/aid/test/pytest/testAggregating.py
ioflo/aid/test/pytest/testBlending.py
ioflo/aio/__init__.py
ioflo/aio/aioing.py
ioflo/aio/wiring.py
ioflo/aio/http/__init__.py
ioflo/aio/http/clienting.py
ioflo/aio/http/httping.py
ioflo/aio/http/serving.py
ioflo/aio/http/test/__init__.py
ioflo/aio/http/test/test_clienting.py
ioflo/aio/http/test/test_serving.py
ioflo/aio/proto/__init__.py
ioflo/aio/proto/devicing.py
ioflo/aio/proto/exchanging.py
ioflo/aio/proto/packeting.py
ioflo/aio/proto/protoing.py
ioflo/aio/proto/stacking.py
ioflo/aio/proto/test/__init__.py
ioflo/aio/proto/test/test_devicing.py
ioflo/aio/proto/test/test_exchanging.py
ioflo/aio/proto/test/test_packeting.py
ioflo/aio/proto/test/test_stacking.py
ioflo/aio/serial/__init__.py
ioflo1.egg-info/PKG-INFO
ioflo1.egg-info/SOURCES.txt
ioflo1.egg-info/dependency_links.txt
ioflo1.egg-info/top_level.txt
