Metadata-Version: 1.1
Name: ioflo1
Version: 1.7.8
Summary: Flow Based Programming Automated Reasoning Engine and Automation Operation System
Home-page: https://github.com/ioflo/ioflo
Author: Samuel M. Smith
Author-email: info@ioflo.com
License: Apache 2.0
Download-URL: https://github.com/ioflo/ioflo/archive/master.zip
Keywords: Automation Operating System Automated Reasoning Engine Flow Based Programming Intelligent Automation Pub/Sub ioflo FloScript
Platform: UNKNOWN
